README.md
setup.cfg
setup.py
pockette/__init__.py
pockette/cli.py
pockette/options.py
pockette/pocket_handler.py
pockette/pocket_setup.py
pockette.egg-info/PKG-INFO
pockette.egg-info/SOURCES.txt
pockette.egg-info/dependency_links.txt
pockette.egg-info/entry_points.txt
pockette.egg-info/requires.txt
pockette.egg-info/top_level.txt
tests/__init__.py
tests/functional/__init__.py
tests/functional/test_pocket.py
tests/functional/test_read.py
tests/functional/test_report.py
tests/functional/test_search.py
tests/functional/test_setup.py