Metadata-Version: 2.1
Name: pockette
Version: 0.0.1
Summary: Command line tools for working with Pocket
Home-page: https://github.com/ThomasThoren/pockette
Author: Thomas Thoren
License: MIT
Keywords: Pocket,CLI
Platform: UNKNOWN
Classifier: License :: OSI Approved :: MIT License
Classifier: Programming Language :: Python :: 3.7
Classifier: Programming Language :: Python :: 3.8
Classifier: Programming Language :: Python :: 3.9
Requires-Python: >=3.7.0
Provides-Extra: dev
